melodic/__init__.py
melodic/client.py
melodic/constants.py
melodic/exceptions.py
melodic/models.py
melodic/network.py
melodic/parser.py
melodic/storage.py
melodic-3.0.0.dist-info/METADATA
melodic-3.0.0.dist-info/WHEEL
melodic-3.0.0.dist-info/licenses/LICENSE
melodic-3.0.0.dist-info/RECORD
