Metadata-Version: 2.4
Name: melodic
Version: 3.0.0
Summary: An asynchronous client for fetching lyrical discographies of music artists.
Project-URL: Homepage, https://github.com/filming/melodic
Project-URL: Repository, https://github.com/filming/melodic
Project-URL: Issues, https://github.com/filming/melodic/issues
Project-URL: Changelog, https://github.com/filming/melodic/blob/master/CHANGELOG.md
Author: Filming
License: MIT License
License-File: LICENSE
Keywords: python,python3
Classifier: Development Status :: 3 - Alpha
Classifier: Intended Audience :: Developers
Classifier: License :: OSI Approved :: MIT License
Classifier: Programming Language :: Python :: 3
Classifier: Programming Language :: Python :: 3.10
Classifier: Programming Language :: Python :: 3.11
Classifier: Programming Language :: Python :: 3.12
Classifier: Programming Language :: Python :: 3.13
Requires-Python: >=3.10
Requires-Dist: aiohttp-socks>=0.10.1
Requires-Dist: aiohttp>=3.12.15
Requires-Dist: aiosqlite>=0.21.0
Requires-Dist: beautifulsoup4>=4.13.5
Requires-Dist: lxml>=6.0.1
Provides-Extra: dev
Requires-Dist: commitizen>=4.8.3; extra == 'dev'
Requires-Dist: mypy>=1.16.1; extra == 'dev'
Requires-Dist: pre-commit>=4.2.0; extra == 'dev'
Requires-Dist: ruff>=0.12.1; extra == 'dev'
Requires-Dist: twine>=6.1.0; extra == 'dev'
